oarepo_search/__init__.py
oarepo_search/config.py
oarepo_search/ext.py
oarepo_search/proxies.py
oarepo_search/query_parsers.py
oarepo_search/search.py
oarepo_search/utils.py
oarepo_search/version.py
tests/__init__.py
tests/conftest.py
tests/test_ext.py
tests/test_query_parser.py
tests/test_utils.py
tests/test_version.py
tests/mappings/__init__.py
tests/mappings/v7/__init__.py
tests/mappings/v7/records/__init__.py
tests/mappings/v7/records/record-v1.0.0.json
oarepo_search-1.0.1.dist-info/LICENSE
oarepo_search-1.0.1.dist-info/METADATA
oarepo_search-1.0.1.dist-info/WHEEL
oarepo_search-1.0.1.dist-info/entry_points.txt
oarepo_search-1.0.1.dist-info/top_level.txt
oarepo_search-1.0.1.dist-info/RECORD
