Metadata-Version: 2.1
Name: oarepo-search
Version: 1.0.1
Summary: OArepo module that adds support for communities
Home-page: https://github.com/oarepo/oarepo-search
Author: Daniel Kopecký
Author-email: Daniel.Kopecky@techlib.cz
License: MIT
Keywords: invenio oarepo search
Platform: any
Classifier: Environment :: Web Environment
Classifier: Intended Audience :: Developers
Classifier: License :: OSI Approved :: MIT License
Classifier: Operating System :: OS Independent
Classifier: Programming Language :: Python
Classifier: Topic :: Internet :: WWW/HTTP :: Dynamic Content
Classifier: Topic :: Software Development :: Libraries :: Python Modules
Classifier: Programming Language :: Python :: 3
Classifier: Programming Language :: Python :: 3.6
Classifier: Programming Language :: Python :: 3.7
Classifier: Programming Language :: Python :: 3.8
Classifier: Programming Language :: Python :: 3.9
Classifier: Development Status :: 4 - Beta
Requires-Dist: luqum
Provides-Extra: all
Requires-Dist: oarepo[tests] (~=3.3.60) ; extra == 'all'
Requires-Dist: pydocstyle ; extra == 'all'
Requires-Dist: isort ; extra == 'all'
Provides-Extra: tests
Requires-Dist: oarepo[tests] (~=3.3.60) ; extra == 'tests'
Requires-Dist: pydocstyle ; extra == 'tests'
Requires-Dist: isort ; extra == 'tests'
